chessminal/__init__.py
chessminal/classify_moves.py
chessminal/game_review.py
chessminal/main.py
chessminal/openings.py
chessminal/validation.py
chessminal-2.1.3.dist-info/LICENSE
chessminal-2.1.3.dist-info/METADATA
chessminal-2.1.3.dist-info/WHEEL
chessminal-2.1.3.dist-info/entry_points.txt
chessminal-2.1.3.dist-info/top_level.txt
chessminal-2.1.3.dist-info/RECORD
