Metadata-Version: 2.2
Name: chessminal
Version: 2.1.3
Summary: chess.com's paid Game Review feature for free in a terminal.
License-File: LICENSE
Requires-Dist: chess
Requires-Dist: python-chess
Requires-Dist: stockfish
Requires-Dist: requests
Requires-Dist: rich
Dynamic: description
Dynamic: description-content-type
Dynamic: requires-dist
Dynamic: summary
